echad/__init__.py
echad/_base.py
echad/bar.py
echad/consts.py
echad/core.py
echad/datatable.py
echad/dropdown.py
echad/gauge.py
echad/pie.py
echad/assets/_hyperscript.min.js
echad/assets/charty.js
echad/assets/echarts.min.js
echad/assets/htmx.min.js
echad/assets/jexcel.js
echad/assets/tailwind.min.css
echad/assets/theme.js
echad-0.0.5.dist-info/METADATA
echad-0.0.5.dist-info/WHEEL
echad-0.0.5.dist-info/top_level.txt
echad-0.0.5.dist-info/RECORD
